lingodotdev/__init__.py
lingodotdev/engine.py
lingodotdev-1.0.4.dist-info/METADATA
lingodotdev-1.0.4.dist-info/WHEEL
lingodotdev-1.0.4.dist-info/licenses/LICENSE
lingodotdev-1.0.4.dist-info/RECORD
