Metadata-Version: 2.4
Name: lingodotdev
Version: 1.0.4
Summary: Lingo.dev Python SDK
Project-URL: Homepage, https://lingo.dev
Project-URL: Documentation, https://lingo.dev/docs
Project-URL: Repository, https://github.com/lingodotdev/sdk-python
Project-URL: Issues, https://github.com/lingodotdev/sdk-python/issues
Author-email: "Lingo.dev Team" <hi@lingo.dev>
License: Apache-2.0
License-File: LICENSE
Keywords: i18n,lingo.dev,localization,translation
Classifier: Development Status :: 4 - Beta
Classifier: Intended Audience :: Developers
Classifier: License :: OSI Approved :: Apache Software License
Classifier: Operating System :: OS Independent
Classifier: Programming Language :: Python
Classifier: Programming Language :: Python :: 3
Classifier: Programming Language :: Python :: 3.8
Classifier: Programming Language :: Python :: 3.9
Classifier: Programming Language :: Python :: 3.10
Classifier: Programming Language :: Python :: 3.11
Classifier: Programming Language :: Python :: 3.12
Classifier: Topic :: Software Development :: Libraries :: Python Modules
Classifier: Topic :: Software Development :: Localization
Classifier: Topic :: Text Processing :: Linguistic
Requires-Python: >=3.8
Requires-Dist: nanoid>=2.0.0
Requires-Dist: pydantic>=2.0.0
Requires-Dist: requests>=2.25.0
Provides-Extra: dev
Requires-Dist: black>=23.0.0; extra == 'dev'
Requires-Dist: flake8>=6.0.0; extra == 'dev'
Requires-Dist: mypy>=1.0.0; extra == 'dev'
Requires-Dist: pytest-cov>=4.0.0; extra == 'dev'
Requires-Dist: pytest>=7.0.0; extra == 'dev'
Requires-Dist: python-semantic-release>=8.0.0; extra == 'dev'
Requires-Dist: types-requests>=2.25.0; extra == 'dev'
